Metadata-Version: 2.1
Name: rtv
Version: 1.27.1
Summary: A simple terminal viewer for Reddit (Reddit Terminal Viewer)
Home-page: https://github.com/michael-lazar/rtv
Author: Michael Lazar
Author-email: lazar.michael22@gmail.com
License: MIT
Keywords: reddit terminal praw curses
Platform: UNKNOWN
Classifier: Intended Audience :: End Users/Desktop
Classifier: Environment :: Console :: Curses
Classifier: Operating System :: MacOS :: MacOS X
Classifier: Operating System :: POSIX
Classifier: Natural Language :: English
Classifier: Programming Language :: Python :: 2.7
Classifier: Programming Language :: Python :: 3.4
Classifier: Programming Language :: Python :: 3.5
Classifier: Programming Language :: Python :: 3.6
Classifier: Programming Language :: Python :: 3.7
Classifier: Topic :: Terminals
Classifier: Topic :: Internet :: WWW/HTTP :: Dynamic Content :: Message Boards
Classifier: Topic :: Internet :: WWW/HTTP :: Dynamic Content :: News/Diary
License-File: LICENSE
License-File: AUTHORS.rst
Requires-Dist: beautifulsoup4
Requires-Dist: decorator
Requires-Dist: kitchen
Requires-Dist: requests (>=2.4.0)
Requires-Dist: six
Requires-Dist: mailcap-fix ; python_version<'3.6'
Provides-Extra: test
Requires-Dist: coveralls ; extra == 'test'
Requires-Dist: pytest (>=3.1.0) ; extra == 'test'
Requires-Dist: coverage ; extra == 'test'
Requires-Dist: mock ; extra == 'test'
Requires-Dist: pylint ; extra == 'test'
Requires-Dist: vcrpy ; extra == 'test'
